{
  "white_label": { "code": "tx" },
  "need": {
    "external_name": "tx_first_step_staffing",
    "category_type": {
      "external_name": "tx_job_resources",
      "name": "Job resources",
      "icon": "job_resources"
    },
    "type_short": ["job resources"],
    "translations": {
      "name": "First Step Staffing",
      "description": "First Step Staffing helps people facing barriers to employment find jobs and keep them. They place job seekers with local employers and provide wraparound support including transportation to and from work, job readiness coaching, workplace communication support, and long-term retention services.",
      "link": "https://www.firststepstaffing.com/application",
      "warning": "",
      "website_description": "Staffing agency connecting Dallas-area job seekers facing barriers to employment with jobs and wraparound support services like transportation and coaching.",
      "notification_message": ""
    },
    "phone_number": "+14698993867",
    "functions": ["tx_first_step_staffing"],
    "counties": ["Dallas"],
    "required_expense_types": [],
    "active": true,
    "low_confidence": false,
    "show_on_current_benefits": true
  }
}
